jeet/__init__.py
jeet-0.1.2.dist-info/METADATA
jeet-0.1.2.dist-info/WHEEL
jeet-0.1.2.dist-info/top_level.txt
jeet-0.1.2.dist-info/RECORD
