Metadata-Version: 2.4
Name: jeet
Version: 0.1.2
Summary: A prank pip package
Author: Sangramjeet Ghosh
Dynamic: author
Dynamic: summary
